{
  "projects": [
    {
      "name": "Portal Emonkey",
      "category": "Frontend",
      "description": "Sitio web para solicitar y administrar tus créditos emonkey",
      "linkToFront": "https://emonkey.com.co/",
      "image": "emonkey.png",
      "imageAlt": "Captura de la vista móvil de la landing page"
    },
    {
      "name": "Curso de Angular",
      "category": "Frontend",
      "description": "Colección of mini apps organizadas en módulos para aprender Angular",
      "linkToFront": "https://angular-course-ianortiz.vercel.app/",
      "image": "angular-course.png",
      "imageAlt": "Logo de Angular con leyenda 'Angular 15 course'"
    },
    {
      "name": "Clone de Youtube",
      "category": "Frontend",
      "description": "App hecha como un reto personal. La página principal y la barra de busqueda consumen la API de Youtube",
      "linkToFront": "https://youtube-clone-ianortiz.vercel.app/",
      "image": "youtube-clone.png",
      "imageAlt": "Logo de Youtube con la palabra 'clone' debajo"
    },
    {
      "name": "Chat app",
      "category": "Fullstack",
      "description": "Proyecto hecho para explorar el stack MERN, y los web sockets",
      "linkToFront": "https://chat-app-ianortiz.vercel.app/",
      "image": "chat-app.jpg",
      "imageAlt": "Imagen stock de un chat"
    },
    {
      "name": "API de ropa",
      "category": "Backend",
      "description": "API creada con Express para crear articulos de ropa",
      "linkToBack": "https://ianmarcos.github.io/clothes-api-form/",
      "image": "clothes-api.png",
      "imageAlt": "Captura del formulario creado para demostrar la API"
    }
  ]
}
